{
	"info": {
		"_postman_id": "f658e618-81c4-414c-b574-ca445ce930f0",
		"name": "MyCollection",
		"description": "This collection will run all smoke APIs",
		"schema": "https://schema.getpostman.com/json/collection/v2.1.0/collection.json",
		"_exporter_id": "31643912"
	},
	"item": [
		{
			"name": "SmokeTest",
			"item": [
				{
					"name": "GetUsers",
					"event": [
						{
							"listen": "test",
							"script": {
								"exec": [
									"pm.test(\"Response time is less than 200ms\", function () {\r",
									"    pm.test(\"Status code is 200\", function () {\r",
									"        pm.response.to.have.status(200);\r",
									"    });\r",
									"    pm.expect(pm.response.responseTime).to.be.below(200);\r",
									"});\r",
									"pm.test(\"Body matches string\", function () {\r",
									"    pm.expect(pm.response.text()).to.include(\"last_name\");\r",
									"});\r",
									"\r",
									"pm.test('Total number of pages', function (){\r",
									"    var jsonData = pm.response.json()\r",
									"    pm.expect(jsonData.total_pages).to.eql(2);\r",
									"});\r",
									"\r",
									"pm.test('Verify first_name', function () {\r",
									"    var jsonData = pm.response.json()\r",
									"    pm.expect(jsonData.data[0].first_name).to.eql('George');\r",
									"})"
								],
								"type": "text/javascript"
							}
						}
					],
					"request": {
						"method": "GET",
						"header": [],
						"url": {
							"raw": "https://reqres.in/api/users?page=1",
							"protocol": "https",
							"host": [
								"reqres",
								"in"
							],
							"path": [
								"api",
								"users"
							],
							"query": [
								{
									"key": "page",
									"value": "1"
								}
							]
						}
					},
					"response": []
				}
			]
		},
		{
			"name": "RegressionTest",
			"item": [
				{
					"name": "CreateUser",
					"event": [
						{
							"listen": "test",
							"script": {
								"exec": [
									"pm.test(\"Successfully Created\", function () {\r",
									"    pm.response.to.have.status(201);\r",
									"});"
								],
								"type": "text/javascript"
							}
						}
					],
					"request": {
						"method": "POST",
						"header": [],
						"body": {
							"mode": "raw",
							"raw": "{\r\n    \"name\": \"Olatunde\",\r\n    \"job\": \"Olukoya\"\r\n}",
							"options": {
								"raw": {
									"language": "json"
								}
							}
						},
						"url": {
							"raw": "https://reqres.in/api/users",
							"protocol": "https",
							"host": [
								"reqres",
								"in"
							],
							"path": [
								"api",
								"users"
							]
						}
					},
					"response": []
				},
				{
					"name": "DeleteUser",
					"event": [
						{
							"listen": "test",
							"script": {
								"exec": [
									"\r",
									"pm.test(\"Status code is 200\", function () {\r",
									"    pm.response.to.have.status(204);\r",
									"});"
								],
								"type": "text/javascript"
							}
						}
					],
					"request": {
						"method": "DELETE",
						"header": [],
						"url": {
							"raw": "https://reqres.in/api/users/2",
							"protocol": "https",
							"host": [
								"reqres",
								"in"
							],
							"path": [
								"api",
								"users",
								"2"
							]
						}
					},
					"response": []
				}
			]
		},
		{
			"name": "SingleUser",
			"request": {
				"method": "GET",
				"header": [],
				"url": {
					"raw": "https://reqres.in/api/users/2",
					"protocol": "https",
					"host": [
						"reqres",
						"in"
					],
					"path": [
						"api",
						"users",
						"2"
					]
				}
			},
			"response": []
		},
		{
			"name": "UserNotFound",
			"request": {
				"method": "GET",
				"header": [],
				"url": {
					"raw": "https://reqres.in/api/users/23",
					"protocol": "https",
					"host": [
						"reqres",
						"in"
					],
					"path": [
						"api",
						"users",
						"23"
					]
				}
			},
			"response": []
		},
		{
			"name": "ListUsers",
			"request": {
				"method": "GET",
				"header": [],
				"url": {
					"raw": "https://reqres.in/api/unknown",
					"protocol": "https",
					"host": [
						"reqres",
						"in"
					],
					"path": [
						"api",
						"unknown"
					]
				}
			},
			"response": []
		}
	]
}